DeltaAgent/LICENSE
DeltaAgent/README.md
DeltaAgent/__init__.py
DeltaAgent/fetch_data/__init__.py
DeltaAgent/fetch_data/fetch_parquet_files/__init__.py
DeltaAgent/get_azure_service_client/__init__.py
DeltaAgent/parse_log_as_df/__init__.py
DeltaAgent/parse_log_as_df/get_pqt_info_from_log/__init__.py
DeltaAgent/parse_log_as_df/get_pqt_info_from_log/get_file_info_df/__init__.py
DeltaAgent/parse_log_as_df/get_pqt_info_from_log/get_file_info_df/get_commits_ls/__init__.py
DeltaAgent/parse_log_as_df/get_pqt_info_from_log/get_file_info_df/keep_valid_and_attach_ptn/__init__.py
DeltaAgent/parse_log_as_df/get_pqt_info_from_log/parse_jsonl_as_dict/__init__.py
DeltaAgent/validate_attrs/__init__.py
deltaagent-0.0.11.dist-info/METADATA
deltaagent-0.0.11.dist-info/WHEEL
deltaagent-0.0.11.dist-info/top_level.txt
deltaagent-0.0.11.dist-info/RECORD
