Metadata-Version: 2.4
Name: DeltaAgent
Version: 0.0.11
Summary: A library used to fetch data from deltalake tables locally.
Author-email: Cody Xiaozhan Yang <x.yang@cloudfmgroup.com>
License: MIT License
Keywords: deltalake,python,local,parquet
Classifier: Programming Language :: Python :: 3
Classifier: License :: OSI Approved :: MIT License
Classifier: Operating System :: OS Independent
Requires-Python: >=3.8
Requires-Dist: tqdm
Requires-Dist: pandas
Requires-Dist: adlfs
Requires-Dist: Office365-REST-Python-Client
